Metadata-Version: 1.1
Name: pyext
Version: 0.6
Summary: Simple Python extensions.
Home-page: UNKNOWN
Author: Ryan Gonzalez
Author-email: kirbyfan64sos@gmail.com
License: UNKNOWN
Platform: UNKNOWN
Classifier: License :: OSI Approved :: MIT License
Classifier: Programming Language :: Python :: 2
Classifier: Programming Language :: Python :: 3
